Metadata-Version: 1.0
Name: scrapy-rotated-cookies
Version: 0.0.1
Summary: A Scrapy middleware to attach cookie to request rotatedly
Home-page: UNKNOWN
Author: alex-wang
Author-email: UNKNOWN
License: UNKNOWN
Platform: UNKNOWN
